minsort/__init__.py
minsort/main.py
minsort-0.1.0.dist-info/LICENSE
minsort-0.1.0.dist-info/METADATA
minsort-0.1.0.dist-info/WHEEL
minsort-0.1.0.dist-info/RECORD
