Metadata-Version: 2.3
Name: minsort
Version: 0.1.0
Summary: 
Author: Kuga
Author-email: celerval5@gmail.com
Requires-Python: >=3.10.0,<3.11
Classifier: Programming Language :: Python :: 3
Classifier: Programming Language :: Python :: 3.10
Requires-Dist: sympy (>=1.12,<2.0)
